oebuild/__init__.py
oebuild/__main__.py
oebuild/auto_completion.py
oebuild/bblayers.py
oebuild/check_docker_tag.py
oebuild/command.py
oebuild/configure.py
oebuild/const.py
oebuild/docker_proxy.py
oebuild/local_conf.py
oebuild/m_log.py
oebuild/oebuild_parser.py
oebuild/ogit.py
oebuild/parse_compile.py
oebuild/parse_env.py
oebuild/parse_template.py
oebuild/spec.py
oebuild/util.py
oebuild/version.py
oebuild/app/__init__.py
oebuild/app/main.py
oebuild/app/conf/compile.yaml.sample
oebuild/app/conf/config.yaml
oebuild/app/conf/manifest_banner
oebuild/app/conf/oebuild.sh
oebuild/app/conf/plugins.yaml
oebuild/app/plugins/bitbake/__init__.py
oebuild/app/plugins/bitbake/base_build.py
oebuild/app/plugins/bitbake/bitbake.py
oebuild/app/plugins/bitbake/in_container.py
oebuild/app/plugins/bitbake/in_host.py
oebuild/app/plugins/clear/clear.py
oebuild/app/plugins/demo/demo.py
oebuild/app/plugins/deploy/__init__.py
oebuild/app/plugins/deploy/com_target.py
oebuild/app/plugins/deploy/deploy_target.py
oebuild/app/plugins/generate/generate.py
oebuild/app/plugins/init/init.py
oebuild/app/plugins/m_env/m_env.py
oebuild/app/plugins/m_plugin/m_plugin.py
oebuild/app/plugins/manifest/manifest.py
oebuild/app/plugins/run_qemu/run_qemu.py
oebuild/app/plugins/update/update.py
oebuild/bb/__init__.py
oebuild/bb/utils.py
yocto_oebuild-0.0.44.dist-info/LICENSE.txt
yocto_oebuild-0.0.44.dist-info/METADATA
yocto_oebuild-0.0.44.dist-info/WHEEL
yocto_oebuild-0.0.44.dist-info/entry_points.txt
yocto_oebuild-0.0.44.dist-info/top_level.txt
yocto_oebuild-0.0.44.dist-info/RECORD
