Metadata-Version: 2.1
Name: yocto-oebuild
Version: 0.0.44
Home-page: https://github.com/tangwei55170831/yocto_oebuild
Author: alichinese
Author-email: 
Classifier: Programming Language :: Python :: 3
Classifier: License :: OSI Approved :: Apache Software License
Classifier: Operating System :: POSIX :: Linux
Requires-Python: >=3.8
License-File: LICENSE.txt
Requires-Dist: setuptools
Requires-Dist: packaging
Requires-Dist: PyYaml
Requires-Dist: docker
Requires-Dist: GitPython
Requires-Dist: colorama
Requires-Dist: ruamel.yaml
Requires-Dist: dataclasses
Requires-Dist: reprint
Requires-Dist: prettytable
Requires-Dist: kconfiglib
